.hgignore
CHANGES.txt
LICENSE.txt
README.txt
bootstrap.py
buildout.cfg
setup.py
js/__init__.py
js.jquery_simplemodal.egg-info/PKG-INFO
js.jquery_simplemodal.egg-info/SOURCES.txt
js.jquery_simplemodal.egg-info/dependency_links.txt
js.jquery_simplemodal.egg-info/entry_points.txt
js.jquery_simplemodal.egg-info/namespace_packages.txt
js.jquery_simplemodal.egg-info/not-zip-safe
js.jquery_simplemodal.egg-info/requires.txt
js.jquery_simplemodal.egg-info/top_level.txt
js/jquery_simplemodal/__init__.py
js/jquery_simplemodal/test_jquery.simplemodal.txt
js/jquery_simplemodal/resources/README.txt
js/jquery_simplemodal/resources/jquery.simplemodal.js
js/jquery_simplemodal/resources/jquery.simplemodal.min.js