Metadata-Version: 1.0
Name: js.jquery-simplemodal
Version: 1.4.1
Summary: Fanstatic packaging of jquery.simplemodal
Home-page: UNKNOWN
Author: Fanstatic Developers
Author-email: fanstatic@googlegroups.com
License: BSD
Platform: UNKNOWN
